Workbook

Sheet Resumen
A1: Planilla de costos · Alunza
A2: Tutor Universitario Inteligente para Programación I · Capstone Duoc UC sede Puente Alto · Equipo: B. Pérez, A. Retamal y M. Núñez · Valores en CLP
A4: 1. Costo total del proyecto
A5: Concepto | B5: Monto (CLP) | C5: % del total | D5: Monto (UF) | F5: Detalle
A6: Recurso humano (3 profesionales) | B6: =RRHH!M9 -> 5678043.4 | C6: =B6/$B$12 -> 0.70610402 | D6: =B6/Supuestos!$B$6 -> 138.26838 | F6: 540 h × costo hora productiva de cada integrante (hoja RRHH).
A7: Infraestructura cloud y herramientas | B7: =Infraestructura!I16 -> 661375 | C7: =B7/$B$12 -> 0.082246561 | D7: =B7/Supuestos!$B$6 -> 16.105415 | F7: Vercel, Supabase, Azure, dominio y licencias (hoja Infraestructura).
A8: Equipamiento y otros directos | B8: ='Otros costos'!G9 -> 653076.92 | C8: =B8/$B$12 -> 0.081214638 | D8: =B8/Supuestos!$B$6 -> 15.903345 | F8: Depreciación de notebooks, internet/energía y material (hoja Otros costos).
A9: Subtotal directo | B9: =SUM(B6:B8) -> 6992495.3 | C9: =B9/$B$12 -> 0.86956522 | D9: =B9/Supuestos!$B$6 -> 170.27714
A10: Gastos generales y administración | B10: =B9*Supuestos!$B$31 -> 349624.77 | C10: =B10/$B$12 -> 0.043478261 | D10: =B10/Supuestos!$B$6 -> 8.5138569 | F10: Recargo porcentual (hoja Supuestos).
A11: Contingencia | B11: =B9*Supuestos!$B$32 -> 699249.53 | C11: =B11/$B$12 -> 0.086956522 | D11: =B11/Supuestos!$B$6 -> 17.027714 | F11: Reserva para imprevistos (hoja Supuestos).
A12: COSTO TOTAL ESTIMADO DEL PROYECTO | B12: =B9+B10+B11 -> 8041369.6 | C12: =B12/$B$12 -> 1 | D12: =B12/Supuestos!$B$6 -> 195.81871 | F12: Debe coincidir con el total de la hoja 'Por sprint'.
A13: Equivalente en US$ | B13: =B12/Supuestos!$B$7 -> 8693.3726
A14: Control: diferencia con hoja 'Por sprint' | B14: =B12-'Por sprint'!N14 -> 0
A16: 2. Comparación con la línea base de la Fase 1
A17: Concepto | B17: Fase 1 (CLP) | C17: Planilla realista (CLP) | D17: Variación (CLP) | E17: Variación % | F17: Explicación
A18: Recurso humano | B18: =Supuestos!$B$34*Supuestos!$B$35 -> 4320000 | C18: =B6 -> 5678043.4 | D18: =C18-B18 -> 1358043.4 | E18: =IF(B18=0,0,D18/B18) -> 0.3143619 | F18: Fase 1 usó $8.000/h; aquí se calcula el costo empresa real de un profesional junior.
A19: Costos directos (infraestructura y otros) | B19: =Supuestos!$B$36 -> 265000 | C19: =B7+B8 -> 1314451.9 | D19: =C19-B19 -> 1049451.9 | E19: =IF(B19=0,0,D19/B19) -> 3.9601959 | F19: Fase 1 consideraba planes gratuitos; aquí se valoriza un entorno productivo con planes de pago.
A20: Gastos generales y contingencia | B20: 0 | C20: =B10+B11 -> 1048874.3 | D20: =C20-B20 -> 1048874.3 | E20: =IF(B20=0,0,D20/B20) -> 0 | F20: No se consideraban en la línea base.
A21: Total | B21: =SUM(B18:B20) -> 4585000 | C21: =SUM(C18:C20) -> 8041369.6 | D21: =C21-B21 -> 3456369.6 | E21: =IF(B21=0,0,D21/B21) -> 0.75384289
A23: 3. Indicadores
A24: Indicador | B24: Valor | F24: Fórmula
A25: Costo hora productiva promedio (CLP/h) | B25: =RRHH!K9 -> 10514.895 | F25: Promedio de los tres integrantes.
A26: Costo total por semana (CLP) | B26: =B12/Supuestos!$B$15 -> 446742.76 | F26: Costo total ÷ 18 semanas.
A27: Costo por punto de historia (CLP) | B27: =B12/Supuestos!$B$37 -> 43703.096 | F27: Costo total ÷ 184 puntos.
A28: Costo por historia de usuario (CLP) | B28: =B12/Supuestos!$B$38 -> 297828.51 | F28: Costo total ÷ 27 historias.
A29: Horas totales del proyecto | B29: =RRHH!L9 -> 540 | F29: Suma de las horas por sprint.
A30: Costo de nube mensual en operación (CLP/mes) | B30: =Infraestructura!I16/4 -> 165343.75 | F30: Total de infraestructura ÷ 4 meses facturados; referencia para operar el piloto.
A32: Los supuestos, fuentes y límites de este modelo están en las hojas 'Supuestos' y 'Fuentes'. Es una estimación para planificación académica, no una cotización.

Sheet Supuestos
A1: Supuestos y parámetros
A2: Celdas en azul = datos editables (amarillo = supuestos clave). Todo el libro se recalcula a partir de esta hoja.
A4: Parámetro | B4: Valor | C4: Unidad | D4: Fuente / criterio
A5: 1. Indicadores económicos (Chile)
A6: Valor UF (1 oct 2026) | B6: 41065.38 | C6: CLP | D6: Banco Central de Chile vía calcular.cl (valor 1/10/2026). Actualizar al cierre del informe.
A7: Dólar observado de referencia | B7: 925 | C7: CLP/USD | D7: Dólar observado BCCh: $920,26 (20/08/2026), $911,77 (10/08/2026) y $936,16 (29/07/2026). Se usa 925 como valor medio prudente.
A8: Ingreso Mínimo Mensual (IMM) | B8: 553553 | C8: CLP | D8: Ley 21.830, vigente desde el 1/05/2026 (base del tope de gratificación).
A9: 2. Jornada y calendario
A10: Horas semanales de jornada | B10: 42 | C10: horas | D10: Ley de 40 horas: jornada de 42 h semanales desde el 26/04/2026 (verificar contrato).
A11: Días hábiles por semana | B11: 5 | C11: días | D11: Jornada de lunes a viernes.
A12: Vacaciones anuales | B12: 15 | C12: días hábiles | D12: Feriado legal anual básico (Código del Trabajo, art. 67).
A13: Feriados en día hábil (2026, estimado) | B13: 10 | C13: días | D13: Calendario 2026: 1/1, 3/4, 1/5, 21/5, 29/6, 16/7, 18/9, 12/10, 8/12 y 25/12 (estimación del equipo).
A14: Horas productivas anuales por persona | B14: =$B$10*52-($B$12+$B$13)*$B$10/$B$11 -> 1974 | C14: horas | D14: Cálculo: horas contractuales anuales menos vacaciones y feriados. Se usa para llegar al costo por hora productiva.
A15: Duración del proyecto | B15: 18 | C15: semanas | D15: Plan de Fase 1: 11/08/2026 al 17/12/2026.
A16: Cantidad de sprints | B16: 9 | C16: sprints | D16: S0 a S8, de 2 semanas cada uno.
A17: Duración en meses | B17: =$B$15*12/52 -> 4.1538462 | C17: meses | D17: Semanas × 12 / 52.
A18: 3. Remuneraciones y cargas del empleador (profesional contratado como dependiente)
A19: Cotización empleador (COE, incluye SIS) | B19: 0.035 | C19: % imponible | D19: Desde el 1/08/2026 el aporte del empleador sube de 1% a 3,5% (Ley 21.735); incluye el SIS. Fuentes: 24horas.cl y KPMG (jul-2026).
A20: Seguro de cesantía (empleador) | B20: 0.024 | C20: % imponible | D20: Contrato indefinido: 2,4% a cargo del empleador (KPMG, jul-2026).
A21: Mutual / Ley 16.744 (tasa base) | B21: 0.0093 | C21: % imponible | D21: Tasa base 0,93%; el adicional depende de la actividad (oficina: se asume solo la base).
A22: Gratificación legal | B22: 0.25 | C22: % remuneración | D22: Art. 50 Código del Trabajo: 25% de la remuneración con tope mensual de 4,75 IMM / 12.
A23: Tope mensual de gratificación | B23: =4.75*$B$8/12 -> 219114.73 | C23: CLP | D23: 4,75 × IMM / 12.
A24: Tope imponible (90 UF) | B24: =90*$B$6 -> 3695884.2 | C24: CLP | D24: Tope imponible 2026: 90 UF para AFP, salud y mutual.
A25: 4. Equipamiento y gastos asociados al puesto de trabajo
A26: Notebook de desarrollo (precio) | B26: 900000 | C26: CLP/equipo | D26: Equipo de gama media para desarrollo web; se imputa solo su depreciación durante el proyecto.
A27: Vida útil contable del notebook | B27: 36 | C27: meses | D27: Criterio de depreciación lineal a 3 años.
A28: Internet y energía por persona | B28: 25000 | C28: CLP/mes | D28: Trabajo híbrido/remoto: proporción de internet y electricidad (estimación del equipo).
A29: Impresión y material de presentación | B29: 30000 | C29: CLP | D29: Informe final, afiches y material de defensa.
A30: 5. Recargos
A31: Gastos generales y administración | B31: 0.05 | C31: % subtotal | D31: Coordinación, contabilidad y soporte; recargo sobre el subtotal directo.
A32: Contingencia | B32: 0.1 | C32: % subtotal | D32: Reserva para imprevistos y riesgos de estimación (práctica habitual 10%-15%).
A33: 6. Línea base de la Fase 1 (Acta de Constitución)
A34: Horas totales del proyecto | B34: 540 | C34: horas | D34: Fase 1: 540 horas (60 por sprint).
A35: Tarifa hora usada en Fase 1 | B35: 8000 | C35: CLP/hora | D35: Fase 1: $8.000 por hora.
A36: Costos directos Fase 1 | B36: 265000 | C36: CLP | D36: Fase 1: tope de costos directos.
A37: Puntos de historia del backlog | B37: 184 | C37: puntos | D37: Product Backlog Fase 1: 27 historias, 184 puntos.
A38: Historias de usuario | B38: 27 | C38: HU | D38: Product Backlog Fase 1.

Sheet RRHH
A1: Recurso humano profesional
A2: Costo empresa de un profesional contratado como dependiente, convertido a costo por hora productiva.
A5: Integrante | B5: Rol en Alunza | C5: Sueldo base bruto mensual | D5: Gratificación legal | E5: Remuneración imponible | F5: COE (incl. SIS) | G5: Seguro cesantía | H5: Mutual 0,93% | I5: Costo empresa mensual | J5: Horas productivas anuales | K5: Costo hora productiva | L5: Horas asignadas | M5: Costo total proyecto
A6: Marcelo Núñez | B6: Product Owner, backend y seguridad | C6: 1400000 | D6: =MIN(C6*Supuestos!$B$22,Supuestos!$B$23) -> 219114.73 | E6: =MIN(C6+D6,Supuestos!$B$24) -> 1619114.7 | F6: =E6*Supuestos!$B$19 -> 56669.016 | G6: =E6*Supuestos!$B$20 -> 38858.753 | H6: =E6*Supuestos!$B$21 -> 15057.767 | I6: =C6+D6+F6+G6+H6 -> 1729700.3 | J6: =Supuestos!$B$14 -> 1974 | K6: =I6*12/J6 -> 10514.895 | L6: ='Por sprint'!D14 -> 189 | M6: =K6*L6 -> 1987315.2
A7: Abraham Retamal | B7: Datos, IA/RAG y calidad | C7: 1400000 | D7: =MIN(C7*Supuestos!$B$22,Supuestos!$B$23) -> 219114.73 | E7: =MIN(C7+D7,Supuestos!$B$24) -> 1619114.7 | F7: =E7*Supuestos!$B$19 -> 56669.016 | G7: =E7*Supuestos!$B$20 -> 38858.753 | H7: =E7*Supuestos!$B$21 -> 15057.767 | I7: =C7+D7+F7+G7+H7 -> 1729700.3 | J7: =Supuestos!$B$14 -> 1974 | K7: =I7*12/J7 -> 10514.895 | L7: ='Por sprint'!E14 -> 180 | M7: =K7*L7 -> 1892681.1
A8: Benjamin Pérez | B8: UX/UI, frontend y documentación | C8: 1400000 | D8: =MIN(C8*Supuestos!$B$22,Supuestos!$B$23) -> 219114.73 | E8: =MIN(C8+D8,Supuestos!$B$24) -> 1619114.7 | F8: =E8*Supuestos!$B$19 -> 56669.016 | G8: =E8*Supuestos!$B$20 -> 38858.753 | H8: =E8*Supuestos!$B$21 -> 15057.767 | I8: =C8+D8+F8+G8+H8 -> 1729700.3 | J8: =Supuestos!$B$14 -> 1974 | K8: =I8*12/J8 -> 10514.895 | L8: ='Por sprint'!F14 -> 171 | M8: =K8*L8 -> 1798047.1
A9: Total / promedio | C9: =SUM(C6:C8) -> 4200000 | D9: =SUM(D6:D8) -> 657344.19 | E9: =SUM(E6:E8) -> 4857344.2 | F9: =SUM(F6:F8) -> 170007.05 | G9: =SUM(G6:G8) -> 116576.26 | H9: =SUM(H6:H8) -> 45173.301 | I9: =SUM(I6:I8) -> 5189100.8 | K9: =AVERAGE(K6:K8) -> 10514.895 | L9: =SUM(L6:L8) -> 540 | M9: =SUM(M6:M8) -> 5678043.4
A11: Criterio salarial: ingeniero/a de software junior (0-2 años) en Chile. Referencias: promedio Indeed $1.559.610 (sep-2026); pretensiones promedio $1.125.840 en ChileTrabajos (jul-2026); sueldo a 4° año Informática $1.550.000 (MiFuturo/Duoc UC). Se fija $1.400.000 bruto como valor central; ajústelo por integrante.
A12: Costo empresa = sueldo + gratificación legal + COE (3,5%) + seguro de cesantía (2,4%) + mutual (0,93%). El costo hora divide el costo anual por las horas realmente productivas (descontando vacaciones y feriados).
A13: No se incluyen indemnizaciones ni bonos (se asume contrato por la duración del proyecto). Si el equipo se valoriza como honorarios, reemplace las cargas por la retención vigente de la boleta de honorarios.
A14: Las horas asignadas provienen de la hoja 'Por sprint' (540 h en total, igual a la línea base de la Fase 1).

Sheet Por sprint
A1: Costo por sprint
A2: Horas por integrante (azul) × costo hora de la hoja RRHH. Distribución base: la del Sprint Backlog 2 (21/20/19 h = 60 h) replicada en cada sprint; reemplazar por horas reales.
A4: Sprint | B4: Semanas | C4: Foco | D4: Horas Marcelo | E4: Horas Abraham | F4: Horas Benjamin | G4: Horas totales | H4: Costo RRHH | I4: ¿Infra activa? (1/0) | J4: Infraestructura asignada | K4: Otros directos | L4: Subtotal directo | M4: Gastos generales + contingencia | N4: Total sprint | O4: Acumulado | P4: % acumulado
A5: S0 | B5: 1-2 | C5: Alineación y descubrimiento | D5: 21 | E5: 20 | F5: 19 | G5: =SUM(D5:F5) -> 60 | H5: =D5*RRHH!$K$6+E5*RRHH!$K$7+F5*RRHH!$K$8 -> 630893.71 | I5: 0 | J5: =IF(I5=1,Infraestructura!$I$16/SUM($I$5:$I$13),0) -> 0 | K5: ='Otros costos'!$G$9/Supuestos!$B$16 -> 72564.103 | L5: =H5+J5+K5 -> 703457.82 | M5: =L5*(Supuestos!$B$31+Supuestos!$B$32) -> 105518.67 | N5: =L5+M5 -> 808976.49 | O5: =SUM($N$5:N5) -> 808976.49 | P5: =O5/$N$14 -> 0.10060183
A6: S1 | B6: 3-4 | C6: Definición y diseño | D6: 21 | E6: 20 | F6: 19 | G6: =SUM(D6:F6) -> 60 | H6: =D6*RRHH!$K$6+E6*RRHH!$K$7+F6*RRHH!$K$8 -> 630893.71 | I6: 0 | J6: =IF(I6=1,Infraestructura!$I$16/SUM($I$5:$I$13),0) -> 0 | K6: ='Otros costos'!$G$9/Supuestos!$B$16 -> 72564.103 | L6: =H6+J6+K6 -> 703457.82 | M6: =L6*(Supuestos!$B$31+Supuestos!$B$32) -> 105518.67 | N6: =L6+M6 -> 808976.49 | O6: =SUM($N$5:N6) -> 1617953 | P6: =O6/$N$14 -> 0.20120366
A7: S2 | B7: 5-6 | C7: Plataforma base | D7: 21 | E7: 20 | F7: 19 | G7: =SUM(D7:F7) -> 60 | H7: =D7*RRHH!$K$6+E7*RRHH!$K$7+F7*RRHH!$K$8 -> 630893.71 | I7: 1 | J7: =IF(I7=1,Infraestructura!$I$16/SUM($I$5:$I$13),0) -> 94482.143 | K7: ='Otros costos'!$G$9/Supuestos!$B$16 -> 72564.103 | L7: =H7+J7+K7 -> 797939.96 | M7: =L7*(Supuestos!$B$31+Supuestos!$B$32) -> 119690.99 | N7: =L7+M7 -> 917630.95 | O7: =SUM($N$5:N7) -> 2535583.9 | P7: =O7/$N$14 -> 0.31531742
A8: S3 | B8: 7-8 | C8: Contenido y estructura | D8: 21 | E8: 20 | F8: 19 | G8: =SUM(D8:F8) -> 60 | H8: =D8*RRHH!$K$6+E8*RRHH!$K$7+F8*RRHH!$K$8 -> 630893.71 | I8: 1 | J8: =IF(I8=1,Infraestructura!$I$16/SUM($I$5:$I$13),0) -> 94482.143 | K8: ='Otros costos'!$G$9/Supuestos!$B$16 -> 72564.103 | L8: =H8+J8+K8 -> 797939.96 | M8: =L8*(Supuestos!$B$31+Supuestos!$B$32) -> 119690.99 | N8: =L8+M8 -> 917630.95 | O8: =SUM($N$5:N8) -> 3453214.9 | P8: =O8/$N$14 -> 0.42943118
A9: S4 | B9: 9-10 | C9: Primer incremento integrado | D9: 21 | E9: 20 | F9: 19 | G9: =SUM(D9:F9) -> 60 | H9: =D9*RRHH!$K$6+E9*RRHH!$K$7+F9*RRHH!$K$8 -> 630893.71 | I9: 1 | J9: =IF(I9=1,Infraestructura!$I$16/SUM($I$5:$I$13),0) -> 94482.143 | K9: ='Otros costos'!$G$9/Supuestos!$B$16 -> 72564.103 | L9: =H9+J9+K9 -> 797939.96 | M9: =L9*(Supuestos!$B$31+Supuestos!$B$32) -> 119690.99 | N9: =L9+M9 -> 917630.95 | O9: =SUM($N$5:N9) -> 4370845.8 | P9: =O9/$N$14 -> 0.54354495
A10: S5 | B10: 11-12 | C10: Diagnóstico, feedback y RAG | D10: 21 | E10: 20 | F10: 19 | G10: =SUM(D10:F10) -> 60 | H10: =D10*RRHH!$K$6+E10*RRHH!$K$7+F10*RRHH!$K$8 -> 630893.71 | I10: 1 | J10: =IF(I10=1,Infraestructura!$I$16/SUM($I$5:$I$13),0) -> 94482.143 | K10: ='Otros costos'!$G$9/Supuestos!$B$16 -> 72564.103 | L10: =H10+J10+K10 -> 797939.96 | M10: =L10*(Supuestos!$B$31+Supuestos!$B$32) -> 119690.99 | N10: =L10+M10 -> 917630.95 | O10: =SUM($N$5:N10) -> 5288476.8 | P10: =O10/$N$14 -> 0.65765871
A11: S6 | B11: 13-14 | C11: Panel docente y calidad | D11: 21 | E11: 20 | F11: 19 | G11: =SUM(D11:F11) -> 60 | H11: =D11*RRHH!$K$6+E11*RRHH!$K$7+F11*RRHH!$K$8 -> 630893.71 | I11: 1 | J11: =IF(I11=1,Infraestructura!$I$16/SUM($I$5:$I$13),0) -> 94482.143 | K11: ='Otros costos'!$G$9/Supuestos!$B$16 -> 72564.103 | L11: =H11+J11+K11 -> 797939.96 | M11: =L11*(Supuestos!$B$31+Supuestos!$B$32) -> 119690.99 | N11: =L11+M11 -> 917630.95 | O11: =SUM($N$5:N11) -> 6206107.7 | P11: =O11/$N$14 -> 0.77177247
A12: S7 | B12: 15-16 | C12: Gobierno y cierre funcional | D12: 21 | E12: 20 | F12: 19 | G12: =SUM(D12:F12) -> 60 | H12: =D12*RRHH!$K$6+E12*RRHH!$K$7+F12*RRHH!$K$8 -> 630893.71 | I12: 1 | J12: =IF(I12=1,Infraestructura!$I$16/SUM($I$5:$I$13),0) -> 94482.143 | K12: ='Otros costos'!$G$9/Supuestos!$B$16 -> 72564.103 | L12: =H12+J12+K12 -> 797939.96 | M12: =L12*(Supuestos!$B$31+Supuestos!$B$32) -> 119690.99 | N12: =L12+M12 -> 917630.95 | O12: =SUM($N$5:N12) -> 7123738.7 | P12: =O12/$N$14 -> 0.88588624
A13: S8 | B13: 17-18 | C13: Estabilización y defensa | D13: 21 | E13: 20 | F13: 19 | G13: =SUM(D13:F13) -> 60 | H13: =D13*RRHH!$K$6+E13*RRHH!$K$7+F13*RRHH!$K$8 -> 630893.71 | I13: 1 | J13: =IF(I13=1,Infraestructura!$I$16/SUM($I$5:$I$13),0) -> 94482.143 | K13: ='Otros costos'!$G$9/Supuestos!$B$16 -> 72564.103 | L13: =H13+J13+K13 -> 797939.96 | M13: =L13*(Supuestos!$B$31+Supuestos!$B$32) -> 119690.99 | N13: =L13+M13 -> 917630.95 | O13: =SUM($N$5:N13) -> 8041369.6 | P13: =O13/$N$14 -> 1
A14: Total | D14: =SUM(D5:D13) -> 189 | E14: =SUM(E5:E13) -> 180 | F14: =SUM(F5:F13) -> 171 | G14: =SUM(G5:G13) -> 540 | H14: =SUM(H5:H13) -> 5678043.4 | I14: =SUM(I5:I13) -> 7 | J14: =SUM(J5:J13) -> 661375 | K14: =SUM(K5:K13) -> 653076.92 | ... N14: =SUM(N5:N13) -> 8041369.6
A16: Nota: los sprints S0 y S1 no tienen infraestructura pagada porque el desarrollo de software parte en S2 (semana 5). Cambie la columna I si activa servicios antes.

Sheet Infraestructura
A1: Infraestructura cloud y herramientas
A2: Servicios mensualizados en USD y convertidos a CLP con el dólar de referencia. Use 'Incluir' (1/0) para activar o desactivar cada servicio.
A5: Servicio | B5: Plan / uso en Alunza | C5: Proveedor | D5: USD unitario | E5: Cantidad | F5: Meses | G5: Incluir (1/0) | H5: Total USD | I5: Total CLP | J5: Nota
A6: Frontend Next.js + previews + Vercel Sandbox | B6: Vercel Pro (asientos que despliegan) | C6: Vercel | D6: 20 | E6: 3 | F6: 4 | G6: 1 | H6: =D6*E6*F6*G6 -> 240 | I6: =H6*Supuestos!$B$7 -> 222000 | J6: US$20 por asiento/mes e incluye US$20 de crédito de uso por asiento (Vercel, may-2026). La plan Hobby no permite uso comercial.
A7: Consumo adicional de Vercel Sandbox | B7: Uso sobre el crédito incluido | C7: Vercel | D7: 5 | E7: 1 | F7: 4 | G7: 1 | H7: =D7*E7*F7*G7 -> 20 | I7: =H7*Supuestos!$B$7 -> 18500 | J7: Active CPU US$0,128/hora; carga baja de un curso piloto, se reserva un margen.
A8: Base de datos, Auth, Storage y pgvector | B8: Supabase Pro | C8: Supabase | D8: 25 | E8: 1 | F8: 4 | G8: 1 | H8: =D8*E8*F8*G8 -> 100 | I8: =H8*Supuestos!$B$7 -> 92500 | J8: US$25/mes por proyecto; permite RLS, backups y evita la pausa por inactividad del plan gratuito.
A9: API NestJS en contenedor | B9: Azure Container Apps (consumo) | C9: Microsoft Azure | D9: 10 | E9: 1 | F9: 4 | G9: 1 | H9: =D9*E9*F9*G9 -> 40 | I9: =H9*Supuestos!$B$7 -> 37000 | J9: Estimación: contenedor pequeño con escala a cero; el plan de consumo incluye una cuota gratuita mensual.
A10: IA generativa y embeddings | B10: Azure OpenAI (pago por uso) | C10: Microsoft Azure | D10: 15 | E10: 1 | F10: 4 | G10: 1 | H10: =D10*E10*F10*G10 -> 60 | I10: =H10*Supuestos!$B$7 -> 55500 | J10: Estimación para un piloto con 2 organizaciones sintéticas; pistas con RAG y embeddings de material oficial.
A11: Dominio del proyecto | B11: Dominio .com / .cl anual | C11: NIC / registrador | D11: 15 | E11: 1 | F11: 1 | G11: 1 | H11: =D11*E11*F11*G11 -> 15 | I11: =H11*Supuestos!$B$7 -> 13875 | J11: Costo anual referencial; se imputa una sola vez.
A12: Repositorio y CI/CD | B12: GitHub (repositorio público + Actions) | C12: GitHub | D12: 0 | E12: 1 | F12: 4 | G12: 1 | H12: =D12*E12*F12*G12 -> 0 | I12: =H12*Supuestos!$B$7 -> 0 | J12: Plan gratuito suficiente para lint, Jest, Cypress y build.
A13: Diseño de interfaces | B13: Figma Starter | C13: Figma | D13: 0 | E13: 1 | F13: 4 | G13: 1 | H13: =D13*E13*F13*G13 -> 0 | I13: =H13*Supuestos!$B$7 -> 0 | J13: Plan gratuito para mockups; pasar a Professional (US$15/mes) si se requiere trabajo colaborativo avanzado.
A14: Monitoreo y errores | B14: Plan gratuito de observabilidad | C14: Varios | D14: 0 | E14: 1 | F14: 4 | G14: 1 | H14: =D14*E14*F14*G14 -> 0 | I14: =H14*Supuestos!$B$7 -> 0 | J14: Logs de Azure/Vercel y plan gratuito de herramienta de errores.
A15: Asistente de código con IA | B15: Licencia individual para desarrollo | C15: Varios | D15: 20 | E15: 3 | F15: 4 | G15: 1 | H15: =D15*E15*F15*G15 -> 240 | I15: =H15*Supuestos!$B$7 -> 222000 | J15: Herramienta habitual en equipos profesionales; desactivar si el equipo no la paga.
A16: Total infraestructura y herramientas | H16: =SUM(H6:H15) -> 715 | I16: =SUM(I6:I15) -> 661375
A18: Meses facturados: se consideran 4 (sep-dic 2026), pues el desarrollo parte en S2. Los precios deben validarse en la calculadora oficial de cada proveedor antes de contratar.

Sheet Otros costos
A1: Equipamiento y otros costos directos
A2: Costos asociados al puesto de trabajo y al cierre del proyecto.
A5: Ítem | B5: Criterio de cálculo | C5: Cantidad | D5: Costo unitario (CLP) | E5: Divisor | F5: Meses | G5: Total CLP | H5: Nota
A6: Depreciación de notebooks | B6: Cantidad × precio ÷ vida útil × meses de proyecto | C6: 3 | D6: =Supuestos!$B$26 -> 900000 | E6: =Supuestos!$B$27 -> 36 | F6: =Supuestos!$B$17 -> 4.1538462 | G6: =C6*D6/E6*F6 -> 311538.46 | H6: Un equipo por integrante; solo se imputa la parte consumida.
A7: Internet y energía | B7: Cantidad × costo mensual × meses | C7: 3 | D7: =Supuestos!$B$28 -> 25000 | E7: — | F7: =Supuestos!$B$17 -> 4.1538462 | G7: =C7*D7*F7 -> 311538.46 | H7: Parte proporcional del trabajo remoto/híbrido.
A8: Impresión y material de defensa | B8: Monto único | C8: 1 | D8: =Supuestos!$B$29 -> 30000 | E8: — | F8: — | G8: =C8*D8 -> 30000 | H8: Informe final, afiches y presentación.
A9: Total otros costos directos | G9: =SUM(G6:G8) -> 653076.92

Sheet Fuentes
A1: Fuentes y límites del modelo
A2: Consultadas en septiembre-octubre de 2026.
A4: Dato | B4: Fuente
A5: Sueldos de ingeniería de software en Chile | B5: Indeed Chile (actualizado 8/9/2026): promedio $1.559.610; ChileTrabajos (jul-2026): pretensiones promedio $1.125.840; redimin.cl con cifras MiFuturo/Duoc UC: $1.550.000 a 4° año de Informática.
A6: Cotización del empleador desde agosto 2026 | B6: 24horas.cl y Mega (30/07/2026): sube de 1% a 3,5%; KPMG Chile, alerta laboral (2/07/2026): AFC 2,4% y COE; Superintendencia de Pensiones (spensiones.cl).
A7: Ingreso Mínimo Mensual | B7: Ley 21.830 (D.O. 22/06/2026): $553.553 desde el 1/05/2026.
A8: UF y dólar | B8: calcular.cl (UF 1/10/2026: $41.065,38); Banco Central de Chile (dólar observado $920,26 el 20/08/2026).
A9: Precios Vercel | B9: Documentación de Vercel Pro (jul-2026) y makerkit.dev (verificado en may-2026): US$20/asiento/mes con crédito de US$20; Active CPU US$0,128/hora.
A10: Precios Supabase | B10: Plan Pro desde US$25/mensuales (nocode.mba, 2026); el cómputo adicional puede elevar el costo.
A11: Azure Container Apps y Azure OpenAI | B11: Estimaciones del equipo para un piloto de bajo volumen; validar en la calculadora de precios de Azure.
A12: Línea base de Fase 1 | B12: Acta de Constitución y Roadmap Ágil de Alunza: 540 h, $8.000/h, $265.000 de costos directos, 27 HU, 184 puntos.
A13: Límites del modelo | B13: No incluye impuestos a las ventas, indemnizaciones, bonos ni costos de oportunidad. Las horas por sprint replican la distribución del Sprint 2 hasta contar con horas reales. Los precios de nube cambian con frecuencia: confirmar antes de usarlos como compromiso.
